scimple/__init__.py
scimple/graph.py
scimple/kafka.py
scimple/plot.py
scimple/pygal_utils.py
scimple/pyspark_utils.py
scimple/stats.py
scimple/utils.py
scimple/scimple_data/CHARGES_phenyl-Fe-porphyirine-CO2-Me_4_rel
scimple/scimple_data/adult.txt
scimple/scimple_data/ek_InTP_CO2_Me_4_graphene_W_r2_k.dat
scimple/scimple_data/phenyl-Fe-porphyirine-CO2-Me_4_rel.xyz
scimple/scimple_data/spark-streaming-kafka-0-8-assembly_2.11-2.3.0.jar
scimple-1.11.5.dist-info/METADATA
scimple-1.11.5.dist-info/WHEEL
scimple-1.11.5.dist-info/top_level.txt
scimple-1.11.5.dist-info/RECORD
