Metadata-Version: 2.1
Name: scimple
Version: 1.11.5
Summary: Scimplify Ploting, Graph manipulation, Spark Streaming & Kafka and other tools
Home-page: http://github.com/EnzoBnl/Scimple
Author: Enzo Bonnal
Author-email: enzobonnal@gmail.com
License: UNKNOWN
Platform: UNKNOWN
Requires-Dist: matplotlib
Requires-Dist: numpy
Requires-Dist: pandas
Requires-Dist: pyspark
Requires-Dist: pyarrow
Requires-Dist: networkx
